mctech_discovery/__init__.py
mctech_discovery/testmain.py
mctech_discovery/discovery/__init__.py
mctech_discovery/discovery/eureka_discovery_client.py
mctech_discovery/discovery/eureka_discovery_health_indicator.py
mctech_discovery/discovery/local_discovery_client.py
mctech_discovery/lifecycle/__init__.py
mctech_discovery/lifecycle/lifecycle.py
mctech_discovery/rpc/__init__.py
mctech_discovery/rpc/_rpc_types.py
mctech_discovery/rpc/request_context.py
mctech_discovery/rpc/rpc_client.py
mctech_discovery/rpc/web_error.py
mctech_discovery/rpc/ep/__init__.py
mctech_discovery/rpc/ep/ep_request.py
mctech_discovery/rpc/ep/httpx_clients.py
mctech_discovery/rpc/ep/internal_rpc.py
mctech_discovery/rpc/ep/simple_ep_request.py
mctech_discovery/rpc/lb/__init__.py
mctech_discovery/rpc/lb/_lb_types.py
mctech_discovery/rpc/lb/direct_loadbalancer.py
mctech_discovery/rpc/lb/discovery_service_loadbalancer.py
mctech_discovery/rpc/lb/local_service_loadabalancer.py
mctech_discovery/rpc/lb/retry_loadbalancer.py
mctech_discovery/rpc/rule/__init__.py
mctech_discovery/rpc/rule/abstarct_rule.py
mctech_discovery/rpc/rule/simple_rule.py
mctech_discovery-1.2.3.dist-info/METADATA
mctech_discovery-1.2.3.dist-info/WHEEL
mctech_discovery-1.2.3.dist-info/top_level.txt
mctech_discovery-1.2.3.dist-info/RECORD
