Metadata-Version: 2.1
Name: mctech-discovery
Version: 1.2.3
Summary: UNKNOWN
Home-page: UNKNOWN
License: UNKNOWN
Platform: UNKNOWN
Requires-Dist: log4py
Requires-Dist: netifaces
Requires-Dist: py-eureka-client
Requires-Dist: httpx
Requires-Dist: mctech-actuator
Requires-Dist: mctech-core
Requires-Dist: websocket-client
